cert_chain_resolver/__init__.py
cert_chain_resolver/api.py
cert_chain_resolver/cli.py
cert_chain_resolver/exceptions.py
cert_chain_resolver/models.py
cert_chain_resolver/py.typed
cert_chain_resolver/resolver.py
cert_chain_resolver/utils.py
cert_chain_resolver/castore/__init__.py
cert_chain_resolver/castore/base_store.py
cert_chain_resolver/castore/file_system.py
cert_chain_resolver-1.4.1.dist-info/licenses/LICENSE.txt
tests/__init__.py
tests/_utils.py
tests/conftest.py
tests/fixtures.py
tests/test_api.py
tests/test_castore.py
tests/test_castore_filesystem.py
tests/test_cli.py
tests/test_models.py
tests/test_resolver.py
tests/test_utils.py
cert_chain_resolver-1.4.1.dist-info/METADATA
cert_chain_resolver-1.4.1.dist-info/WHEEL
cert_chain_resolver-1.4.1.dist-info/entry_points.txt
cert_chain_resolver-1.4.1.dist-info/top_level.txt
cert_chain_resolver-1.4.1.dist-info/RECORD
