Metadata-Version: 2.4
Name: cert_chain_resolver
Version: 1.4.1
Summary: Resolve / obtain the certificate intermediates of a x509 cert
Home-page: https://github.com/rkoopmans/python-certificate-chain-resolver
Author: Remco Koopmans
Author-email: me@remcokoopmans.com
License: MIT
Classifier: Programming Language :: Python :: 2.7
Classifier: Programming Language :: Python :: 3
Classifier: Programming Language :: Python :: 3.8
Classifier: Programming Language :: Python :: 3.9
Classifier: Programming Language :: Python :: 3.10
Classifier: Programming Language :: Python :: 3.11
Classifier: Programming Language :: Python :: 3.12
Classifier: Programming Language :: Python :: 3.13
Classifier: Programming Language :: Python :: 3.14
Classifier: License :: OSI Approved :: MIT License
Classifier: Operating System :: OS Independent
License-File: LICENSE.txt
Requires-Dist: cryptography>=3.1
Provides-Extra: certifi
Requires-Dist: certifi; extra == "certifi"
Dynamic: author
Dynamic: author-email
Dynamic: classifier
Dynamic: description
Dynamic: description-content-type
Dynamic: home-page
Dynamic: license
Dynamic: license-file
Dynamic: provides-extra
Dynamic: requires-dist
Dynamic: summary
